{"context": [{"content": "그래서 인제 단백질이랑 지방 위주에 어~ 식사 방법으로 좀 바꿔나가고 있거든요.", "speaker": "붕어"}, {"content": "근데 건강해지는 것도 같고 또 신랑도 혈압도 좀 조절이 됐고 좋은 거 같아서 꾸준히 한 번 해보려고 하거든요.", "speaker": "붕어"}, {"content": "오히려 고기를 많이 먹고 이러면 부식비가 많이 나올 거라고 생각이 드는데 또 그렇지 않다고 하더라고요.", "speaker": "붕어"}, {"content": "그래서 한 번 꾸준히 해서 어떤지 경과를 조금 보고 싶어서 하고 있는 중이에요.", "speaker": "붕어"}], "option": [{"word": "더", "items": [{"pos": "부사", "definition": "계속하여. 또는 그 위에 보태어."}, {"pos": "부사", "definition": "어떤 기준보다 정도가 심하게. 또는 그 이상으로."}, {"pos": "어미", "definition": "과거 어느 때에 직접 경험하여 알게 된 사실을 현재의 말하는 장면에 그대로 옮겨 와서 전달한다는 뜻을 나타내는 어미."}]}, {"word": "좀", "items": [{"pos": "부사", "definition": "‘조금’의 준말."}, {"pos": "부사", "definition": "‘조금’의 준말."}, {"pos": "부사", "definition": "부탁이나 동의를 구할 때 말을 부드럽게 하기 위하여 삽입하는 말."}]}, {"word": "조금", "items": [{"pos": "명사", "definition": "적은 정도나 분량."}, {"pos": "명사", "definition": "짧은 동안."}, {"pos": "부사", "definition": "정도나 분량이 적게."}]}, {"word": "좀더", "items": [{"pos": "부사", "definition": "‘조금’의 준말."}, {"pos": "부사", "definition": "‘조금’의 준말."}, {"pos": "부사", "definition": "부탁이나 동의를 구할 때 말을 부드럽게 하기 위하여 삽입하는 말."}]}], "solution": 1}