{"context": [{"content": "외할머니가 지금 80세인데도 되게 정정하시고 그래가지고 또 퇴직 기간을 조금 늘리는 게 더 좋지 않을까라는 생각을 많이 하고 있는 것 같아요.", "speaker": "돌맹"}, {"content": "그리고 노인 복지에 관한 정보를 어떻게 더 정확하게 홍보할 수 있는 방법이 있을까요?", "speaker": "돌맹"}, {"content": "어~ 일단은 이제 청소년들에게는 이제 학교에서 선생님들이 홍보하는 게 제일 효과적일 것 같고 이제 스무 살들이나 그런 분들한테는 이제 동사무소 봉사 같은 거 있잖아요. 그런 봉사를 통해서", "speaker": "붕어"}, {"content": "이제 알리고 또 그런 봉사를 통해 노인분들을 돕는 봉사 이제 복지 같은 곳에서 봉사하는 거랑 이제 학교에서 홍보를 하는 게 제일 크다고 보는 것 같아요.", "speaker": "붕어"}], "option": [{"word": "것이", "items": [{"pos": "의존 명사", "definition": "사물, 일, 현상 따위를 추상적으로 이르는 말."}, {"pos": "의존 명사", "definition": "사람을 낮추어 이르거나 동물을 이르는 말."}, {"pos": "의존 명사", "definition": "그 사람의 소유물임을 나타내는 말."}]}, {"word": "건", "items": [{"pos": "명사", "definition": "어떤 일이나 문제를 일으킬 만한 특정한 일이나 사건."}, {"pos": "의존 명사", "definition": "사건, 서류, 안건 따위를 세는 단위."}, {"pos": "어미", "definition": "‘-거나’의 준말."}]}, {"word": "게", "items": [{"pos": "대명사", "definition": "‘거기’의 준말."}, {"pos": "대명사", "definition": "‘거기’의 준말."}, {"pos": "대명사", "definition": "‘거기’의 준말."}]}, {"word": "것도", "items": [{"pos": "의존 명사", "definition": "사물, 일, 현상 따위를 추상적으로 이르는 말."}, {"pos": "의존 명사", "definition": "사람을 낮추어 이르거나 동물을 이르는 말."}, {"pos": "의존 명사", "definition": "그 사람의 소유물임을 나타내는 말."}]}], "solution": 2}