{"context": [{"content": "우리 지금 학교에서 코로나 사태 때문에 온라인 수업을 하고 있잖아.", "speaker": "붕어"}, {"content": "혹시 오늘도 온라인 수업으로 하는 진행이 되고 있는데 그거에 대해서 어떤 거 같아? 지금 진행되고 있는 상황이 어떤 거 같아?", "speaker": "붕어"}, {"content": "음~ 난 정말 별로라고 생각하고 어~ 난 솔직히 어~ 학교에 가서 약간 다 같이 집중하고 그런 환경에서만 공부가 잘되기 때문에 나 혼자서 집에서 집중해서 공부를 하는 거는 되게 힘들고 그리고 또 우리가 그~ 영상이 올라와 있는 그런 퀴즈만 푸는 게 아니라 그~ 쌍방향 수업도 해야 되잖아.", "speaker": "돌맹"}, {"content": "근데 내가 그때마다 항상 잠이 들더라고.", "speaker": "돌맹"}], "option": [{"word": "무척", "items": [{"pos": "명사", "definition": "모함하여 쫓아내는 일."}, {"pos": "부사", "definition": "다른 것과 견줄 수 없이."}, {"pos": "명사", "definition": "신라 때에, 춤을 추던 악공."}]}, {"word": "정말", "items": [{"pos": "명사", "definition": "‘덴마크’의 음역어."}, {"pos": "명사", "definition": "거짓이 없이 말 그대로임. 또는 그런 말."}, {"pos": "명사", "definition": "겉으로 드러나지 아니한 사실을 말할 때 쓰는 말."}]}, {"word": "잘났어", "items": [{"pos": "동사", "definition": "사회적으로 계속 성공하다."}, {"pos": "동사", "definition": "얼굴이 잘생기거나 예쁘게 생기다."}, {"pos": "동사", "definition": "능력이 남보다 앞서다."}]}, {"word": "참", "items": [{"pos": "명사", "definition": "만조(滿潮) 때의 물."}, {"pos": "명사", "definition": "일을 하다가 일정하게 잠시 쉬는 동안. 한자를 빌려 ‘站’으로 적기도 한다."}, {"pos": "명사", "definition": "일을 시작하여서 일정하게 쉬는 때까지의 사이."}]}], "solution": 1}