{"context": [{"content": "뭐 서장훈이네 이야기도 나오고 그 사람 돈 많지마는 많은 사람들이 더 베풀기 어렵다 그러는데 그런 착한 건물주가 많이 나오니까 어~ 세 세 세상들이 세상 사람들이 그런 사람들 좀 보고 좀 본도 받고 그랬으면 참 좋겠고 자 이 사람 김 씨 부부는 참 그거에 비해 본다면은 참 약간의 운이 없는 사람들 같기도 하고 앞으로 정말 너 김 씨 부부가 어떻게 지금 돼가지고 즈 어떻게 처벌을 받을지 그게 참 궁금하네.", "speaker": "승열"}, {"content": "이~ 처벌을 받긴 받을 텐데 그 처벌받을 때 좀 아까에도 이야기했지만 나는 그 배심원들 제도가 조금 있어야 되지 않나 싶어.", "speaker": "감자"}, {"content": "그래서 내가 만약에 배심원으로 간다고 하면 나는 무죄라고 이야기할 거 같아.", "speaker": "감자"}, {"content": "그다음에 이 강제집행도 지금 너무 우리나라는 개인 재산권을 인정을 하는데 그게 너무 과하게 인정하는 거 아니냐 이런 생각도 들어.", "speaker": "감자"}], "option": [{"word": "저런", "items": [{"pos": "관형사", "definition": "상태, 모양, 성질 따위가 저러한."}, {"pos": "감탄사", "definition": "‘저리한’이 줄어든 말."}, {"pos": "부사", "definition": "뜻밖에 놀라운 일이나 딱한 일을 보거나 들었을 때 하는 말."}]}, {"word": "이런", "items": [{"pos": "관형사", "definition": "상태, 모양, 성질 따위가 이러한."}, {"pos": "감탄사", "definition": "‘이리한’이 줄어든 말."}, {"pos": "부사", "definition": "뜻밖에 놀라운 일이나 딱한 일을 보거나 들었을 때 하는 말."}]}, {"word": "어떤", "items": [{"pos": "관형사", "definition": "사람이나 사물의 특성, 내용, 상태, 성격이 무엇인지 물을 때 쓰는 말."}, {"pos": "관형사", "definition": "주어진 여러 사물 중 대상으로 삼는 것이 무엇인지 물을 때 쓰는 말."}, {"pos": "관형사", "definition": "대상을 뚜렷이 밝히지 아니하고 이를 때 쓰는 말."}]}, {"word": "그런", "items": [{"pos": "관형사", "definition": "상태, 모양, 성질 따위가 그러한."}, {"pos": "감탄사", "definition": "‘그리한’이 줄어든 말."}, {"pos": "부사", "definition": "뜻밖에 놀라운 일이나 딱한 일을 보거나 들었을 때 하는 말."}]}], "solution": 3}