{"context": [{"content": "누난 운전면허증이 없거든 그~ 여행을 제주도 여행 두 번째 갔을 때 아빠께서 운전 처음 시켰었었던 건가?", "speaker": "승열"}, {"content": "처음 시켰 시키셨지 그지? 운전도", "speaker": "승열"}, {"content": "군대 입대해가지고 평소에는 따지를 못하니까 휴가 때 나와가지고 학원 다니기에는 부담이 되고 뭔가 그 금액을 주고 가야 되나 싶어가지고 혼자 배워가지고 아빠 도움도 받고 해서 면허를 잘 땄는데 운전은 운전면허는 따면 되게 좋은 거 같아.", "speaker": "승열"}, {"content": "언제 물론 당장은 써먹을 때가 없겠지.", "speaker": "승열"}], "option": [{"word": "갔던", "items": [{"pos": "명사", "definition": "경계에 가까운 바깥쪽 부분."}, {"pos": "명사", "definition": "어떤 중심 되는 곳에서 가까운 부분."}, {"pos": "명사", "definition": "그릇 따위의 아가리의 주변."}]}, {"word": "갔었을", "items": [{"pos": "명사", "definition": "경계에 가까운 바깥쪽 부분."}, {"pos": "명사", "definition": "어떤 중심 되는 곳에서 가까운 부분."}, {"pos": "명사", "definition": "그릇 따위의 아가리의 주변."}]}, {"word": "갔을", "items": [{"pos": "명사", "definition": "경계에 가까운 바깥쪽 부분."}, {"pos": "명사", "definition": "어떤 중심 되는 곳에서 가까운 부분."}, {"pos": "명사", "definition": "그릇 따위의 아가리의 주변."}]}, {"word": "왔을", "items": [{"pos": "명사", "definition": "우리나라 성(姓)의 하나. 본관은 해주(海州), 보성(寶城), 동복(同福) 등 60여 본이 현존한다."}, {"pos": "명사", "definition": "문제의 답이 맞았다는 표시."}, {"pos": "수사", "definition": "사에 일을 더한 수. 아라비아 숫자로는 ‘5’, 로마 숫자로는 ‘Ⅴ’로 쓴다."}]}], "solution": 2}