{"context": [{"content": "여름뿐 아니라 다른 계절 음식이 좋아하는 계절 음식이 있나요?", "speaker": "승열"}, {"content": "저는 겨울에 겨 겨울에 있는 날 중 설날에 먹는 떡국이 생각이 납니다.", "speaker": "붕어"}, {"content": "우리나라는 1월 1일에 항상 설날을 지내면서 한 살 더 먹으려고 떡국을 먹는데 그 따뜻한 음식이 겨울이랑 가장 잘 어울리는 것 같아서 겨울 하면은 떡국이 생각이 납니다.", "speaker": "붕어"}, {"content": "가을에는 또 어떤 추억을 갖고 계시나요?", "speaker": "붕어"}], "option": [{"word": "먹고", "items": [{"pos": "명사", "definition": "벼루에 물을 붓고 갈아서 글씨를 쓰거나 그림을 그릴 때 사용하는 검은 물감. 아교를 녹인 물에 그을음을 반죽하여 굳혀서 만든다."}, {"pos": "명사", "definition": "벼루에 먹을 갈아 만든 검은 물."}, {"pos": "명사", "definition": "‘똥’을 달리 이르는 말."}]}, {"word": "먹은", "items": [{"pos": "명사", "definition": "벼루에 물을 붓고 갈아서 글씨를 쓰거나 그림을 그릴 때 사용하는 검은 물감. 아교를 녹인 물에 그을음을 반죽하여 굳혀서 만든다."}, {"pos": "명사", "definition": "벼루에 먹을 갈아 만든 검은 물."}, {"pos": "명사", "definition": "‘똥’을 달리 이르는 말."}]}, {"word": "먹을", "items": [{"pos": "명사", "definition": "벼루에 물을 붓고 갈아서 글씨를 쓰거나 그림을 그릴 때 사용하는 검은 물감. 아교를 녹인 물에 그을음을 반죽하여 굳혀서 만든다."}, {"pos": "명사", "definition": "벼루에 먹을 갈아 만든 검은 물."}, {"pos": "명사", "definition": "‘똥’을 달리 이르는 말."}]}, {"word": "먹는", "items": [{"pos": "명사", "definition": "벼루에 물을 붓고 갈아서 글씨를 쓰거나 그림을 그릴 때 사용하는 검은 물감. 아교를 녹인 물에 그을음을 반죽하여 굳혀서 만든다."}, {"pos": "명사", "definition": "벼루에 먹을 갈아 만든 검은 물."}, {"pos": "명사", "definition": "‘똥’을 달리 이르는 말."}]}], "solution": 3}