{"context": [{"content": "안 먹는 애 하나는 못 먹는 애가 있었고 그러니까 향신료 많이 들어간 이런 음식 빼고는 그냥 나는 먹을 만했는데 그~ 봄에 가서 그런가 저기 있지 그~ 뭐지 노랑 노랑꽃 피는 거 유채야?", "speaker": "승열"}, {"content": "유채 나물만 많이 해주더라고.", "speaker": "승열"}, {"content": "그래서 나물 상추 그런 거에다 삼겹살 해줘서 그런 거만 먹었어.", "speaker": "승열"}, {"content": "그래도 제주도처럼 그~ 유채 나물이 많았어.", "speaker": "승열"}], "option": [{"word": "저런", "items": [{"pos": "관형사", "definition": "상태, 모양, 성질 따위가 저러한."}, {"pos": "감탄사", "definition": "‘저리한’이 줄어든 말."}, {"pos": "부사", "definition": "뜻밖에 놀라운 일이나 딱한 일을 보거나 들었을 때 하는 말."}]}, {"word": "그런", "items": [{"pos": "관형사", "definition": "상태, 모양, 성질 따위가 그러한."}, {"pos": "감탄사", "definition": "‘그리한’이 줄어든 말."}, {"pos": "부사", "definition": "뜻밖에 놀라운 일이나 딱한 일을 보거나 들었을 때 하는 말."}]}, {"word": "이런", "items": [{"pos": "관형사", "definition": "상태, 모양, 성질 따위가 이러한."}, {"pos": "감탄사", "definition": "‘이리한’이 줄어든 말."}, {"pos": "부사", "definition": "뜻밖에 놀라운 일이나 딱한 일을 보거나 들었을 때 하는 말."}]}, {"word": "어떤", "items": [{"pos": "관형사", "definition": "사람이나 사물의 특성, 내용, 상태, 성격이 무엇인지 물을 때 쓰는 말."}, {"pos": "관형사", "definition": "주어진 여러 사물 중 대상으로 삼는 것이 무엇인지 물을 때 쓰는 말."}, {"pos": "관형사", "definition": "대상을 뚜렷이 밝히지 아니하고 이를 때 쓰는 말."}]}], "solution": 1}