{"context": [{"content": "일단은 병역 특례라는 것은 병역의 의무를 대신하는 거잖아.", "speaker": "돌맹"}, {"content": "연구기관이라든지 산업체에서 의무를 다해서 대통령이 정하는 바에 따라서 군 복무 기간을 단축시키는 건데 고것마저도 안 하려고 허위실적을 자료를 이렇게 제출받아서 사진을 찍고 해가지고 봉사시간을 부풀린다는 자체가 학연 지연 뭐 요런 비리들에 의해서 어~ 그~ 발생되는 거라고 해 생각을 해.", "speaker": "돌맹"}, {"content": "병역법 병역제도 대체복무제 병역지정업체 요런 데에서 이런 식으로 어~ 내가 알고 있는 지인 학연 그다음에 비리가 계속 끊임없이 연결고리를 어~ 끊지 않으면 앞으로도 어~ 그~ 장현수에 대한 장현수 선수에 대한 그런 예가 없어지지 않을 거라고 생각을 해.", "speaker": "돌맹"}, {"content": "운동선수뿐만이 아니라 그런 체육 분야에 있는 사람들 예술 분야에 있는 사람들 또한 그런 병역 특례 의무를 대신해야 되는 그런 어~ 물론 성실하게 그 의무를 대신하는 사람들이 있겠지만 어~ 봉사시간을 음~ 봉사하지 않고 그 시간을 다 채워서 어~ 병역에 어~ 벗어나면은 욕은 먹고 어~ 그거를 또 다 채우자니 시간이 아깝고 그래서 음~ 그~ 입영 허가제의 사회복무 그~ 요원 소집할 때 자기들은 실질적으로 근무를 하지 안 않고 그런 시간만 그~ 소요화됐는 그 탁상론에 대해서 그~ 서류화만 됐다는 것 자체가 이런 그~ 음~ 봉사시간 부풀리는 이런 문제가 계속 되풀이된다고 생각해.", "speaker": "돌맹"}], "option": [{"word": "뭐랑", "items": [{"pos": "감탄사", "definition": "‘무어’의 준말."}, {"pos": "대명사", "definition": "‘무어’의 준말."}, {"pos": "대명사", "definition": "이미 일어난 뜻밖의 일이나 상황에 놀라거나 후회하거나 아쉬워하면서 그것을 강조함을 나타내는 말."}]}, {"word": "뭐", "items": [{"pos": "감탄사", "definition": "‘무어’의 준말."}, {"pos": "대명사", "definition": "‘무어’의 준말."}, {"pos": "대명사", "definition": "이미 일어난 뜻밖의 일이나 상황에 놀라거나 후회하거나 아쉬워하면서 그것을 강조함을 나타내는 말."}]}, {"word": "근데", "items": [{"pos": "부사", "definition": "‘그런데’의 준말."}, {"pos": "부사", "definition": "‘그런데’의 준말."}, {"pos": "명사", "definition": "‘고무래’의 방언"}]}, {"word": "이건", "items": [{"pos": "명사", "definition": "건축물 따위를 옮겨 짓거나 세움."}, {"pos": "명사", "definition": "‘이것은’이 줄어든 말."}, {"pos": "명사", "definition": "조선 효종 때의 문인(1614~1662). 자는 자강(子強). 호는 규창(葵窓). 선조의 손자이며 인성군(仁城君) 공(珙)의 아들이다. 시ㆍ서ㆍ화에 뛰어나 삼절(三絕)이라 일컬었다. 저서로 ≪규창집≫이 있다."}]}], "solution": 1}